{
  "commands.clear.done": "&aPulito l'inventario di %s.",
  "commands.crash.done": "&aIl client di %s \u00e8 stato crashato.",
  "commands.feed.done": "&aHai saziato l'appetito di %s.",
  "commands.fly.disable": "&aModalit\u00e0 volo disattivata per %s.",
  "commands.fly.enable": "&aModalit\u00e0 volo attivata per %s.",
  "commands.gamemode.done": "&aImpostata modalit\u00e0 di gioco %s per %s.",
  "commands.gamemode.invalid": "La modalit\u00e0 di gioco fornita non \u00e8 valida.",
  "commands.heal.done": "&a%s \u00e8 stato guarito.",
  "commands.ping.latency": "&aLa tua latenza attuale \u00e8 di %d millisecondi.",
  "commands.ping.pong": "&aPong!",
  "commands.rename.noitem": "Non hai alcun oggetto in mano.",
  "commands.say.format": "&8[&7Avviso&8] &f%s",
  "commands.surface.tp": "&aSei stato teletrasportato in superficie.",
  "commands.world.tp": "&aSei stato teletrasportato in %s.",
  "error.args.boolean": "Parametro non valido: deve essere 'true' o 'false'",
  "error.args.indexinfo": "%s @ Parametro %d",
  "error.args.integer": "Parametro non valido: deve essere un numero intero",
  "error.args.material": "Per favore specifica un oggetto valido.",
  "error.args.number": "Parametro non valido: deve essere un numero",
  "error.args.player": "Parametro non valido: deve essere un giocatore online",
  "error.args.positive": "Parametro non valido: deve essere un numero positivo",
  "error.args.stack": "Parametro non valido: deve essere tra 1 e 64",
  "error.command.internal": "\u00c8 stato riscontrato un errore.",
  "error.command.permission": "Non sei autorizzato ad usare questo comando.",
  "error.command.player": "Questo comando pu\u00f2 essere utilizzato solo come giocatore.",
  "error.command.usage": "Sintassi: %s"
}